{
  "main": {
    "id": "472e90a515bdb311",
    "type": "split",
    "children": [
      {
        "id": "d8f13eb285a58ee6",
        "type": "tabs",
        "dimension": 27.69396551724138,
        "children": [
          {
            "id": "7b32a02b3df97bd0",
            "type": "leaf",
            "state": {
              "type": "markdown",
              "state": {
                "file": "0. mocs/Linguaggi di programmazione.md",
                "mode": "source",
                "source": false
              },
              "icon": "lucide-file",
              "title": "Linguaggi di programmazione"
            }
          },
          {
            "id": "07e2f7fcb78796f0",
            "type": "leaf",
            "state": {
              "type": "markdown",
              "state": {
                "file": "1. lectures/Lecture 09042025110710.md",
                "mode": "source",
                "source": false
              },
              "icon": "lucide-file",
              "title": "Lecture 09042025110710"
            }
          },
          {
            "id": "4d11c7d86f566a3b",
            "type": "leaf",
            "state": {
              "type": "markdown",
              "state": {
                "file": "1. lectures/Lecture 10042025131105.md",
                "mode": "source",
                "source": false
              },
              "icon": "lucide-file",
              "title": "Lecture 10042025131105"
            }
          },
          {
            "id": "796523ddf6227ad8",
            "type": "leaf",
            "state": {
              "type": "markdown",
              "state": {
                "file": "2. notes/Sistema di tipi.md",
                "mode": "source",
                "source": false
              },
              "icon": "lucide-file",
              "title": "Sistema di tipi"
            }
          }
        ],
        "currentTab": 3
      },
      {
        "id": "08dad670807b4996",
        "type": "tabs",
        "dimension": 72.30603448275862,
        "children": [
          {
            "id": "5091dd2830462afe",
            "type": "leaf",
            "state": {
              "type": "markdown",
              "state": {
                "file": "1. lectures/Lecture 16042025110927.md",
                "mode": "source",
                "source": false
              },
              "icon": "lucide-file",
              "title": "Lecture 16042025110927"
            }
          }
        ]
      }
    ],
    "direction": "vertical"
  },
  "left": {
    "id": "cf7ab60d695759ef",
    "type": "split",
    "children": [
      {
        "id": "700edbdca6467b73",
        "type": "tabs",
        "children": [
          {
            "id": "fde22237f1d4b81b",
            "type": "leaf",
            "state": {
              "type": "file-explorer",
              "state": {
                "sortOrder": "byModifiedTime",
                "autoReveal": false
              },
              "icon": "lucide-folder-closed",
              "title": "Files"
            }
          },
          {
            "id": "84188f4c6672f9d8",
            "type": "leaf",
            "state": {
              "type": "search",
              "state": {
                "query": "",
                "matchingCase": false,
                "explainSearch": false,
                "collapseAll": false,
                "extraContext": false,
                "sortOrder": "alphabetical"
              },
              "icon": "lucide-search",
              "title": "Search"
            }
          },
          {
            "id": "8808a1c54be8d13b",
            "type": "leaf",
            "state": {
              "type": "bookmarks",
              "state": {},
              "icon": "lucide-bookmark",
              "title": "Bookmarks"
            }
          }
        ]
      }
    ],
    "direction": "horizontal",
    "width": 267.5
  },
  "right": {
    "id": "d2a30276f1a920cd",
    "type": "split",
    "children": [
      {
        "id": "534c93fde21f83cd",
        "type": "tabs",
        "dimension": 35.67307692307693,
        "children": [
          {
            "id": "c7c5c6af0f3637b7",
            "type": "leaf",
            "state": {
              "type": "backlink",
              "state": {
                "collapseAll": false,
                "extraContext": false,
                "sortOrder": "alphabetical",
                "showSearch": false,
                "searchQuery": "",
                "backlinkCollapsed": false,
                "unlinkedCollapsed": true
              },
              "icon": "links-coming-in",
              "title": "Backlinks"
            }
          },
          {
            "id": "8296ae9f9b6fbbb9",
            "type": "leaf",
            "state": {
              "type": "outgoing-link",
              "state": {
                "file": "1. lectures/Lecture 28022025091715.md",
                "linksCollapsed": false,
                "unlinkedCollapsed": true
              },
              "icon": "links-going-out",
              "title": "Outgoing links from Lecture 28022025091715"
            }
          },
          {
            "id": "bb4dff6f9dab22b8",
            "type": "leaf",
            "state": {
              "type": "tag",
              "state": {
                "sortOrder": "frequency",
                "useHierarchy": true
              },
              "icon": "lucide-tags",
              "title": "Tags"
            }
          },
          {
            "id": "b6848b986be9c4a1",
            "type": "leaf",
            "state": {
              "type": "outline",
              "state": {
                "followCursor": false,
                "showSearch": false,
                "searchQuery": ""
              },
              "icon": "lucide-list",
              "title": "Outline"
            }
          },
          {
            "id": "9981f3c73eda2539",
            "type": "leaf",
            "state": {
              "type": "advanced-tables-toolbar",
              "state": {},
              "icon": "lucide-file",
              "title": "Plugin no longer active"
            }
          },
          {
            "id": "37f6c573762e5d8c",
            "type": "leaf",
            "state": {
              "type": "all-properties",
              "state": {
                "sortOrder": "frequency",
                "showSearch": false,
                "searchQuery": ""
              },
              "icon": "lucide-archive",
              "title": "All properties"
            }
          },
          {
            "id": "6a36b9b141e49926",
            "type": "leaf",
            "state": {
              "type": "file-properties",
              "state": {
                "file": "0. mocs/Linguaggi di programmazione.md"
              },
              "icon": "lucide-info",
              "title": "File properties for Linguaggi di programmazione"
            }
          },
          {
            "id": "11575a6bd2823201",
            "type": "leaf",
            "state": {
              "type": "toggl-report",
              "state": {},
              "icon": "lucide-file",
              "title": "Plugin no longer active"
            }
          },
          {
            "id": "2ecae89c4bdda11b",
            "type": "leaf",
            "state": {
              "type": "toggl-report",
              "state": {},
              "icon": "clock",
              "title": "Toggl Report"
            }
          }
        ]
      },
      {
        "id": "f5e1dd67658d5a90",
        "type": "tabs",
        "dimension": 30.961538461538463,
        "children": [
          {
            "id": "b36b98e17ac7f398",
            "type": "leaf",
            "state": {
              "type": "localgraph",
              "state": {
                "options": {
                  "collapse-filter": true,
                  "search": "",
                  "localJumps": 1,
                  "localBacklinks": true,
                  "localForelinks": true,
                  "localInterlinks": false,
                  "showTags": false,
                  "showAttachments": false,
                  "hideUnresolved": false,
                  "collapse-color-groups": true,
                  "colorGroups": [],
                  "collapse-display": true,
                  "showArrow": false,
                  "textFadeMultiplier": 0,
                  "nodeSizeMultiplier": 1,
                  "lineSizeMultiplier": 1,
                  "collapse-forces": true,
                  "centerStrength": 0.518713248970312,
                  "repelStrength": 10,
                  "linkStrength": 1,
                  "linkDistance": 250,
                  "scale": 0.31214753848498666,
                  "close": true
                }
              },
              "icon": "lucide-git-fork",
              "title": "Graph view"
            }
          }
        ]
      },
      {
        "id": "c31ec5abd0f1721f",
        "type": "tabs",
        "dimension": 33.36538461538461,
        "children": [
          {
            "id": "580e6e077148dbf7",
            "type": "leaf",
            "state": {
              "type": "toggl-report",
              "state": {},
              "icon": "lucide-file",
              "title": "Plugin no longer active"
            }
          }
        ]
      }
    ],
    "direction": "horizontal",
    "width": 296.5,
    "collapsed": true
  },
  "left-ribbon": {
    "hiddenItems": {
      "switcher:Open quick switcher": false,
      "graph:Open graph view": false,
      "canvas:Create new canvas": false,
      "templates:Insert template": false,
      "command-palette:Open command palette": false,
      "audio-recorder:Start/stop recording": false,
      "random-note:Open random note": false,
      "obsidian-excalidraw-plugin:New drawing": false,
      "table-editor-obsidian:Advanced Tables Toolbar": false,
      "obsidian-kanban:Create new board": false,
      "templater-obsidian:Templater": false
    }
  },
  "active": "5091dd2830462afe",
  "lastOpenFiles": [
    "2. notes/Algoritmo di Ford-Fulkerson.md",
    "1. lectures/Lecture 16042025110927.md",
    "2. notes/Variabile libera.md",
    "2. notes/Binder.md",
    "2. notes/Sistema di tipi.md",
    "1. lectures/Lecture 09042025110710.md",
    "1. lectures/Lecture 10042025131105.md",
    "0. mocs/Linguaggi di programmazione.md",
    "1. lectures/Lecture 14042025091835.md",
    "0. mocs/Ottimizzazione combinatoria.md",
    "1. lectures/Lecture 09042025091244.md",
    "1. lectures/Lecture 16042025091309.md",
    "0. mocs/Reti di calcolatori.md",
    "1. lectures/Lecture 14042025111851.md",
    "1. lectures/Lecture 15042025152135.md",
    "0. mocs/Calcolo delle probabilità e statistica.md",
    "2. notes/Eventi generati da una variabile aleatoria.md",
    "1. lectures/Lecture 15042025131630.md",
    "2. notes/Eventi indipendenti.md",
    "1. lectures/Lecture 08042025133009.md",
    "1. lectures/Lecture 11042025131834.md",
    "1. lectures/Lecture 04042025131943.md",
    "2. notes/Distribuzione binomiale.md",
    "2. notes/Varianza.md",
    "2. notes/Distribuzione di Poisson.md",
    "2. notes/Distribuzioni notevoli di variabili aleatorie discrete.md",
    "media/passaggio-per-nome-chiusura.png",
    "media/EIRP.png",
    "media/scope-statico-deep-shallow.png",
    "media/mW-dB-conversion-table.png",
    "media/dope-vector.png",
    "media/sdn.png",
    "media/eccezione-esempio.png",
    "media/ipv6-pacchetto.png",
    "media/openflow-table.png",
    "media/funzioni-ordine-superiore-restituzione2.png",
    "2. notes/Equivalenze regolari.canvas",
    "5. seminars",
    "media/jupiter.jpg.crdownload",
    "media/learning-rate.png.crdownload",
    "media/funzione-convessa.png.crdownload",
    "4. homeworks",
    "3. projects/Untitled",
    "3. projects/aijsodijas.canvas",
    "media/1norm-2norm.jpg.crdownload",
    "netlify.toml~",
    "ads.txt",
    "4913",
    "3. projects/TarBo/Untitled.canvas"
  ]
}